bin/build.sh
bin/clean.sh
bin/release.sh
payloop/__init__.py
payloop/_base.py
payloop/_clients.py
payloop/_config.py
payloop/_constants.py
payloop/_errors.py
payloop/_invoke.py
payloop/_iterable.py
payloop/_iterator.py
payloop/_network.py
payloop/_providers.py
payloop/_sentinel.py
payloop/_streaming.py
payloop/_utils.py
payloop/api/_invocation.py
payloop/api/_workflow.py
payloop-0.6.0.dist-info/METADATA
payloop-0.6.0.dist-info/WHEEL
payloop-0.6.0.dist-info/top_level.txt
payloop-0.6.0.dist-info/RECORD
