Metadata-Version: 2.4
Name: payloop
Version: 0.6.0
Summary: Payloop Python SDK
Author-email: Payloop <noc@trypayloop.com>
Project-URL: Homepage, https://trypayloop.com/
Project-URL: Documentation, https://developers.trypayloop.com/
Project-URL: Repository, https://github.com/PayloopAI/
Classifier: Operating System :: OS Independent
Classifier: Development Status :: 4 - Beta
Classifier: Intended Audience :: Developers
Classifier: Programming Language :: Python :: 3.9
Requires-Python: >=3.9
Requires-Dist: botocore
Requires-Dist: grpcio
Requires-Dist: protobuf
Requires-Dist: requests
Requires-Dist: urllib3
